Metadata-Version: 2.1
Name: scrapy-demo-cloudwatch-log
Version: 1.0.3
Summary: UNKNOWN
Home-page: https://github.com/scalingexcellence/scrapy-demo-cloudwatch-log
Author: Dimitrios Kouzis-Loukas
Author-email: lookfwd@gmail.com
License: MIT
Keywords: scrapy cloudwatch aws json
Platform: UNKNOWN
